fastflatcache/__init__.py
fastflatcache/app/app.py
fastflatcache-0.0.1.dist-info/WHEEL
fastflatcache-0.0.1.dist-info/METADATA
fastflatcache-0.0.1.dist-info/RECORD
